README.rst
setup.py
chptools.egg-info/PKG-INFO
chptools.egg-info/SOURCES.txt
chptools.egg-info/dependency_links.txt
chptools.egg-info/requires.txt
chptools.egg-info/top_level.txt
cptools/__init__.py
cptools/cpt_untils.py
cptools/cptools.py
cptools/main.py