Metadata-Version: 1.0
Name: chptools
Version: 0.0.1
Summary: A series of Chinese processing tools
Home-page: https://github.com/cyzLoveDream/CPTools
Author: Biorad
Author-email: cyz_19930904@163.com
License: MIT
Platform: UNKNOWN
